fastapi_wraps/__init__.py
fastapi_wraps/fastapi_wraps.py
fastapi_wraps/providers.py
fastapi_wraps/py.typed
fastapi_wraps-0.1.4.dist-info/LICENSE
fastapi_wraps-0.1.4.dist-info/WHEEL
fastapi_wraps-0.1.4.dist-info/METADATA
fastapi_wraps-0.1.4.dist-info/RECORD
